fastapi_oidc_simple/__init__.py
fastapi_oidc_simple/oidc.py
fastapi_oidc_simple-0.2.0.dist-info/METADATA
fastapi_oidc_simple-0.2.0.dist-info/WHEEL
fastapi_oidc_simple-0.2.0.dist-info/top_level.txt
fastapi_oidc_simple-0.2.0.dist-info/RECORD
