Metadata-Version: 2.4
Name: fastapi-oidc-simple
Version: 0.2.0
Summary: Simple OIDC integration for FastAPI using Authlib
Author-email: Noidea <noidea1238@gmail.com>
License-Expression: MIT
Project-URL: Homepage, https://github.com/adityasm1238/fastapi-oidc-simple
Classifier: Programming Language :: Python :: 3
Classifier: Operating System :: OS Independent
Requires-Python: >=3.9
Requires-Dist: fastapi>=0.116.0
Requires-Dist: authlib>=1.6.3
Requires-Dist: starlette>=0.47.0
Requires-Dist: httpx>=0.28.0
Requires-Dist: itsdangerous>=2.2.0
